{
  "info": {
    "name": "Task Manager API",
    "description": "Multi-tenant task management API with comprehensive project and task management capabilities",
    "version": "1.0.0",
    "schema": "https://schema.getpostman.com/json/collection/v2.1.0/collection.json"
  },
  "auth": {
    "type": "bearer",
    "bearer": [
      {
        "key": "token",
        "value": "{{authToken}}",
        "type": "string"
      }
    ]
  },
  "variable": [
    {
      "key": "baseUrl",
      "value": "{{baseUrl}}",
      "type": "string"
    },
    {
      "key": "authToken",
      "value": "{{authToken}}",
      "type": "string"
    }
  ],
  "item": [
    {
      "name": "System",
      "item": [
        {
          "name": "Application Status",
          "request": {
            "method": "GET",
            "header": [],
            "url": {
              "raw": "{{baseUrl}}/",
              "host": ["{{baseUrl}}"],
              "path": [""]
            }
          },
          "response": []
        },
        {
          "name": "Health Check",
          "request": {
            "auth": {
              "type": "noauth"
            },
            "method": "GET",
            "header": [],
            "url": {
              "raw": "{{baseUrl}}/health",
              "host": ["{{baseUrl}}"],
              "path": ["health"]
            }
          },
          "response": []
        },
        {
          "name": "Detailed Health Check",
          "request": {
            "auth": {
              "type": "noauth"
            },
            "method": "GET",
            "header": [],
            "url": {
              "raw": "{{baseUrl}}/health/detailed",
              "host": ["{{baseUrl}}"],
              "path": ["health", "detailed"]
            }
          },
          "response": []
        },
        {
          "name": "Admin Health Check",
          "request": {
            "method": "GET",
            "header": [],
            "url": {
              "raw": "{{baseUrl}}/admin/health",
              "host": ["{{baseUrl}}"],
              "path": ["admin", "health"]
            }
          },
          "response": []
        },
        {
          "name": "Application Info",
          "request": {
            "method": "GET",
            "header": [],
            "url": {
              "raw": "{{baseUrl}}/info",
              "host": ["{{baseUrl}}"],
              "path": ["info"]
            }
          },
          "response": []
        }
      ]
    },
    {
      "name": "Authentication",
      "item": [
        {
          "name": "User Login",
          "event": [
            {
              "listen": "test",
              "script": {
                "exec": [
                  "pm.test('Save auth token and user data', function () {",
                  "    var jsonData = pm.response.json();",
                  "    if (jsonData.access_token) {",
                  "        pm.environment.set('authToken', jsonData.access_token);",
                  "        console.log('Auth token saved:', jsonData.access_token);",
                  "    }",
                  "    if (jsonData.user && jsonData.user.user_id) {",
                  "        pm.environment.set('currentUserId', jsonData.user.user_id);",
                  "        pm.environment.set('currentTenantId', jsonData.user.tenant.tenant_id);",
                  "        console.log('User context saved:', {",
                  "            userId: jsonData.user.user_id,",
                  "            tenantId: jsonData.user.tenant.tenant_id,",
                  "            name: jsonData.user.first_name + ' ' + jsonData.user.last_name",
                  "        });",
                  "    }",
                  "});",
                  "",
                  "pm.test('Status code is 200', function () {",
                  "    pm.response.to.have.status(200);",
                  "});",
                  "",
                  "pm.test('Response contains expanded user data', function () {",
                  "    const responseJson = pm.response.json();",
                  "    pm.expect(responseJson).to.have.property('access_token');",
                  "    pm.expect(responseJson).to.have.property('refresh_token');",
                  "    pm.expect(responseJson).to.have.property('user');",
                  "    pm.expect(responseJson.user).to.have.property('first_name');",
                  "    pm.expect(responseJson.user).to.have.property('last_name');",
                  "    pm.expect(responseJson.user).to.have.property('tenant');",
                  "    pm.expect(responseJson.user.tenant).to.have.property('name');",
                  "});"
                ],
                "type": "text/javascript"
              }
            }
          ],
          "request": {
            "auth": {
              "type": "noauth"
            },
            "method": "POST",
            "header": [
              {
                "key": "Content-Type",
                "value": "application/json",
                "type": "text"
              }
            ],
            "body": {
              "mode": "raw",
              "raw": "{\n  \"email\": \"user@company.com\",\n  \"password\": \"MyPassword123!\",\n  \"tenantId\": \"550e8400-e29b-41d4-a716-446655440000\"\n}",
              "options": {
                "raw": {
                  "language": "json"
                }
              }
            },
            "url": {
              "raw": "{{baseUrl}}/auth/login",
              "host": ["{{baseUrl}}"],
              "path": ["auth", "login"]
            }
          },
          "response": []
        },
        {
          "name": "User Signup",
          "event": [
            {
              "listen": "test",
              "script": {
                "exec": [
                  "pm.test('Save auth token and user data after signup', function () {",
                  "    var jsonData = pm.response.json();",
                  "    if (jsonData.access_token) {",
                  "        pm.environment.set('authToken', jsonData.access_token);",
                  "        console.log('Auth token saved after signup:', jsonData.access_token);",
                  "    }",
                  "    if (jsonData.user && jsonData.user.user_id) {",
                  "        pm.environment.set('currentUserId', jsonData.user.user_id);",
                  "        pm.environment.set('currentTenantId', jsonData.user.tenant.tenant_id);",
                  "        console.log('New user and tenant created:', {",
                  "            userId: jsonData.user.user_id,",
                  "            tenantId: jsonData.user.tenant.tenant_id,",
                  "            tenantName: jsonData.tenant.name,",
                  "            userName: jsonData.user.first_name + ' ' + jsonData.user.last_name",
                  "        });",
                  "    }",
                  "});",
                  "",
                  "pm.test('Status code is 201', function () {",
                  "    pm.response.to.have.status(201);",
                  "});",
                  "",
                  "pm.test('Response contains expanded tenant and user data', function () {",
                  "    const responseJson = pm.response.json();",
                  "    pm.expect(responseJson).to.have.property('access_token');",
                  "    pm.expect(responseJson).to.have.property('tenant');",
                  "    pm.expect(responseJson).to.have.property('user');",
                  "    pm.expect(responseJson.user).to.have.property('first_name');",
                  "    pm.expect(responseJson.user).to.have.property('tenant');",
                  "    pm.expect(responseJson.tenant).to.have.property('name');",
                  "});"
                ],
                "type": "text/javascript"
              }
            }
          ],
          "request": {
            "auth": {
              "type": "noauth"
            },
            "method": "POST",
            "header": [
              {
                "key": "Content-Type",
                "value": "application/json",
                "type": "text"
              }
            ],
            "body": {
              "mode": "raw",
              "raw": "{\n  \"tenant_name\": \"Acme Corporation\",\n  \"owner\": {\n    \"first_name\": \"John\",\n    \"last_name\": \"Doe\",\n    \"email\": \"john.doe@company.com\",\n    \"password\": \"SecurePassword123!\"\n  }\n}",
              "options": {
                "raw": {
                  "language": "json"
                }
              }
            },
            "url": {
              "raw": "{{baseUrl}}/auth/signup",
              "host": ["{{baseUrl}}"],
              "path": ["auth", "signup"]
            }
          },
          "response": []
        },
        {
          "name": "Refresh Token",
          "request": {
            "auth": {
              "type": "noauth"
            },
            "method": "POST",
            "header": [
              {
                "key": "Content-Type",
                "value": "application/json",
                "type": "text"
              }
            ],
            "body": {
              "mode": "raw",
              "raw": "{\n  \"refresh_token\": \"550e8400-e29b-41d4-a716-446655440000\"\n}",
              "options": {
                "raw": {
                  "language": "json"
                }
              }
            },
            "url": {
              "raw": "{{baseUrl}}/auth/refresh",
              "host": ["{{baseUrl}}"],
              "path": ["auth", "refresh"]
            }
          },
          "response": []
        },
        {
          "name": "Get Current User",
          "request": {
            "method": "GET",
            "header": [],
            "url": {
              "raw": "{{baseUrl}}/auth/me",
              "host": ["{{baseUrl}}"],
              "path": ["auth", "me"]
            }
          },
          "response": []
        },
        {
          "name": "Logout",
          "request": {
            "method": "POST",
            "header": [],
            "url": {
              "raw": "{{baseUrl}}/auth/logout",
              "host": ["{{baseUrl}}"],
              "path": ["auth", "logout"]
            }
          },
          "response": []
        },
        {
          "name": "Forgot Password",
          "request": {
            "auth": {
              "type": "noauth"
            },
            "method": "POST",
            "header": [
              {
                "key": "Content-Type",
                "value": "application/json",
                "type": "text"
              }
            ],
            "body": {
              "mode": "raw",
              "raw": "{\n  \"email\": \"user@company.com\"\n}",
              "options": {
                "raw": {
                  "language": "json"
                }
              }
            },
            "url": {
              "raw": "{{baseUrl}}/auth/forgot-password",
              "host": ["{{baseUrl}}"],
              "path": ["auth", "forgot-password"]
            }
          },
          "response": []
        },
        {
          "name": "Reset Password",
          "request": {
            "auth": {
              "type": "noauth"
            },
            "method": "POST",
            "header": [
              {
                "key": "Content-Type",
                "value": "application/json",
                "type": "text"
              }
            ],
            "body": {
              "mode": "raw",
              "raw": "{\n  \"token\": \"eyJhbGciOiJIUzI1NiIsInR5cCI6IkpXVCJ9...\",\n  \"password\": \"NewSecurePassword123!\"\n}",
              "options": {
                "raw": {
                  "language": "json"
                }
              }
            },
            "url": {
              "raw": "{{baseUrl}}/auth/reset-password",
              "host": ["{{baseUrl}}"],
              "path": ["auth", "reset-password"]
            }
          },
          "response": []
        }
      ]
    },
    {
      "name": "Tenants (Admin)",
      "item": [
        {
          "name": "List Tenants",
          "request": {
            "method": "GET",
            "header": [],
            "url": {
              "raw": "{{baseUrl}}/tenants?page=1&limit=20",
              "host": ["{{baseUrl}}"],
              "path": ["tenants"],
              "query": [
                {
                  "key": "page",
                  "value": "1"
                },
                {
                  "key": "limit",
                  "value": "20"
                }
              ]
            }
          },
          "response": []
        },
        {
          "name": "Create Tenant",
          "request": {
            "method": "POST",
            "header": [
              {
                "key": "Content-Type",
                "value": "application/json",
                "type": "text"
              }
            ],
            "body": {
              "mode": "raw",
              "raw": "{\n  \"name\": \"New Company\",\n  \"plan\": \"free\"\n}",
              "options": {
                "raw": {
                  "language": "json"
                }
              }
            },
            "url": {
              "raw": "{{baseUrl}}/tenants",
              "host": ["{{baseUrl}}"],
              "path": ["tenants"]
            }
          },
          "response": []
        },
        {
          "name": "Get Tenant",
          "request": {
            "method": "GET",
            "header": [],
            "url": {
              "raw": "{{baseUrl}}/tenants/550e8400-e29b-41d4-a716-446655440000",
              "host": ["{{baseUrl}}"],
              "path": ["tenants", "550e8400-e29b-41d4-a716-446655440000"]
            }
          },
          "response": []
        },
        {
          "name": "Update Tenant",
          "request": {
            "method": "PATCH",
            "header": [
              {
                "key": "Content-Type",
                "value": "application/json",
                "type": "text"
              }
            ],
            "body": {
              "mode": "raw",
              "raw": "{\n  \"name\": \"Updated Company Name\",\n  \"plan\": \"paid\"\n}",
              "options": {
                "raw": {
                  "language": "json"
                }
              }
            },
            "url": {
              "raw": "{{baseUrl}}/tenants/550e8400-e29b-41d4-a716-446655440000",
              "host": ["{{baseUrl}}"],
              "path": ["tenants", "550e8400-e29b-41d4-a716-446655440000"]
            }
          },
          "response": []
        },
        {
          "name": "Delete Tenant",
          "request": {
            "method": "DELETE",
            "header": [],
            "url": {
              "raw": "{{baseUrl}}/tenants/550e8400-e29b-41d4-a716-446655440000",
              "host": ["{{baseUrl}}"],
              "path": ["tenants", "550e8400-e29b-41d4-a716-446655440000"]
            }
          },
          "response": []
        },
        {
          "name": "Export Tenant Data (GDPR)",
          "request": {
            "method": "POST",
            "header": [],
            "url": {
              "raw": "{{baseUrl}}/tenants/550e8400-e29b-41d4-a716-446655440000/data-export",
              "host": ["{{baseUrl}}"],
              "path": ["tenants", "550e8400-e29b-41d4-a716-446655440000", "data-export"]
            }
          },
          "response": []
        },
        {
          "name": "Request Data Deletion (GDPR)",
          "request": {
            "method": "POST",
            "header": [],
            "url": {
              "raw": "{{baseUrl}}/tenants/550e8400-e29b-41d4-a716-446655440000/data-deletion",
              "host": ["{{baseUrl}}"],
              "path": ["tenants", "550e8400-e29b-41d4-a716-446655440000", "data-deletion"]
            }
          },
          "response": []
        },
        {
          "name": "Get Data Retention Status",
          "request": {
            "method": "GET",
            "header": [],
            "url": {
              "raw": "{{baseUrl}}/tenants/550e8400-e29b-41d4-a716-446655440000/data-retention-status",
              "host": ["{{baseUrl}}"],
              "path": ["tenants", "550e8400-e29b-41d4-a716-446655440000", "data-retention-status"]
            }
          },
          "response": []
        }
      ]
    },
    {
      "name": "Users",
      "item": [
        {
          "name": "Get Current User Profile",
          "request": {
            "method": "GET",
            "header": [],
            "url": {
              "raw": "{{baseUrl}}/users/me",
              "host": ["{{baseUrl}}"],
              "path": ["users", "me"]
            }
          },
          "response": []
        },
        {
          "name": "List Users",
          "request": {
            "method": "GET",
            "header": [],
            "url": {
              "raw": "{{baseUrl}}/users?page=1&limit=20&role=member",
              "host": ["{{baseUrl}}"],
              "path": ["users"],
              "query": [
                {
                  "key": "page",
                  "value": "1"
                },
                {
                  "key": "limit",
                  "value": "20"
                },
                {
                  "key": "role",
                  "value": "member"
                }
              ]
            }
          },
          "response": []
        },
        {
          "name": "Create User",
          "request": {
            "method": "POST",
            "header": [
              {
                "key": "Content-Type",
                "value": "application/json",
                "type": "text"
              }
            ],
            "body": {
              "mode": "raw",
              "raw": "{\n  \"email\": \"newuser@domain.com\",\n  \"first_name\": \"Jane\",\n  \"last_name\": \"Smith\",\n  \"role\": \"member\",\n  \"password\": \"NewUserPassword123!\"\n}",
              "options": {
                "raw": {
                  "language": "json"
                }
              }
            },
            "url": {
              "raw": "{{baseUrl}}/users",
              "host": ["{{baseUrl}}"],
              "path": ["users"]
            }
          },
          "response": []
        },
        {
          "name": "Get User",
          "request": {
            "method": "GET",
            "header": [],
            "url": {
              "raw": "{{baseUrl}}/users/550e8400-e29b-41d4-a716-446655440000",
              "host": ["{{baseUrl}}"],
              "path": ["users", "550e8400-e29b-41d4-a716-446655440000"]
            }
          },
          "response": []
        },
        {
          "name": "Update User",
          "request": {
            "method": "PATCH",
            "header": [
              {
                "key": "Content-Type",
                "value": "application/json",
                "type": "text"
              }
            ],
            "body": {
              "mode": "raw",
              "raw": "{\n  \"first_name\": \"Jane Updated\",\n  \"last_name\": \"Smith Updated\"\n}",
              "options": {
                "raw": {
                  "language": "json"
                }
              }
            },
            "url": {
              "raw": "{{baseUrl}}/users/550e8400-e29b-41d4-a716-446655440000",
              "host": ["{{baseUrl}}"],
              "path": ["users", "550e8400-e29b-41d4-a716-446655440000"]
            }
          },
          "response": []
        },
        {
          "name": "Update User Role",
          "request": {
            "method": "PATCH",
            "header": [
              {
                "key": "Content-Type",
                "value": "application/json",
                "type": "text"
              }
            ],
            "body": {
              "mode": "raw",
              "raw": "{\n  \"role\": \"admin\"\n}",
              "options": {
                "raw": {
                  "language": "json"
                }
              }
            },
            "url": {
              "raw": "{{baseUrl}}/users/550e8400-e29b-41d4-a716-446655440000/role",
              "host": ["{{baseUrl}}"],
              "path": ["users", "550e8400-e29b-41d4-a716-446655440000", "role"]
            }
          },
          "response": []
        },
        {
          "name": "Delete User",
          "request": {
            "method": "DELETE",
            "header": [],
            "url": {
              "raw": "{{baseUrl}}/users/550e8400-e29b-41d4-a716-446655440000",
              "host": ["{{baseUrl}}"],
              "path": ["users", "550e8400-e29b-41d4-a716-446655440000"]
            }
          },
          "response": []
        }
      ]
    },
    {
      "name": "Workspaces",
      "item": [
        {
          "name": "List Workspaces",
          "request": {
            "method": "GET",
            "header": [],
            "url": {
              "raw": "{{baseUrl}}/workspaces?archived=false&page=1&limit=20",
              "host": ["{{baseUrl}}"],
              "path": ["workspaces"],
              "query": [
                {
                  "key": "archived",
                  "value": "false"
                },
                {
                  "key": "page",
                  "value": "1"
                },
                {
                  "key": "limit",
                  "value": "20"
                }
              ]
            }
          },
          "response": []
        },
        {
          "name": "Create Workspace",
          "request": {
            "method": "POST",
            "header": [
              {
                "key": "Content-Type",
                "value": "application/json",
                "type": "text"
              }
            ],
            "body": {
              "mode": "raw",
              "raw": "{\n  \"name\": \"Development Team\",\n  \"description\": \"Main development workspace\"\n}",
              "options": {
                "raw": {
                  "language": "json"
                }
              }
            },
            "url": {
              "raw": "{{baseUrl}}/workspaces",
              "host": ["{{baseUrl}}"],
              "path": ["workspaces"]
            }
          },
          "response": []
        },
        {
          "name": "Get Workspace",
          "request": {
            "method": "GET",
            "header": [],
            "url": {
              "raw": "{{baseUrl}}/workspaces/550e8400-e29b-41d4-a716-446655440000",
              "host": ["{{baseUrl}}"],
              "path": ["workspaces", "550e8400-e29b-41d4-a716-446655440000"]
            }
          },
          "response": []
        },
        {
          "name": "Update Workspace",
          "request": {
            "method": "PATCH",
            "header": [
              {
                "key": "Content-Type",
                "value": "application/json",
                "type": "text"
              }
            ],
            "body": {
              "mode": "raw",
              "raw": "{\n  \"name\": \"Updated Workspace Name\",\n  \"description\": \"Updated description\"\n}",
              "options": {
                "raw": {
                  "language": "json"
                }
              }
            },
            "url": {
              "raw": "{{baseUrl}}/workspaces/550e8400-e29b-41d4-a716-446655440000",
              "host": ["{{baseUrl}}"],
              "path": ["workspaces", "550e8400-e29b-41d4-a716-446655440000"]
            }
          },
          "response": []
        },
        {
          "name": "Delete Workspace",
          "request": {
            "method": "DELETE",
            "header": [],
            "url": {
              "raw": "{{baseUrl}}/workspaces/550e8400-e29b-41d4-a716-446655440000",
              "host": ["{{baseUrl}}"],
              "path": ["workspaces", "550e8400-e29b-41d4-a716-446655440000"]
            }
          },
          "response": []
        },
        {
          "name": "Add Member to Workspace",
          "request": {
            "method": "POST",
            "header": [
              {
                "key": "Content-Type",
                "value": "application/json",
                "type": "text"
              }
            ],
            "body": {
              "mode": "raw",
              "raw": "{\n  \"userId\": \"550e8400-e29b-41d4-a716-446655440001\",\n  \"role\": \"member\"\n}",
              "options": {
                "raw": {
                  "language": "json"
                }
              }
            },
            "url": {
              "raw": "{{baseUrl}}/workspaces/550e8400-e29b-41d4-a716-446655440000/members",
              "host": ["{{baseUrl}}"],
              "path": ["workspaces", "550e8400-e29b-41d4-a716-446655440000", "members"]
            }
          },
          "response": []
        },
        {
          "name": "List Workspace Members",
          "request": {
            "method": "GET",
            "header": [],
            "url": {
              "raw": "{{baseUrl}}/workspaces/550e8400-e29b-41d4-a716-446655440000/members",
              "host": ["{{baseUrl}}"],
              "path": ["workspaces", "550e8400-e29b-41d4-a716-446655440000", "members"]
            }
          },
          "response": []
        },
        {
          "name": "Remove Member from Workspace",
          "request": {
            "method": "DELETE",
            "header": [],
            "url": {
              "raw": "{{baseUrl}}/workspaces/550e8400-e29b-41d4-a716-446655440000/members/550e8400-e29b-41d4-a716-446655440001",
              "host": ["{{baseUrl}}"],
              "path": ["workspaces", "550e8400-e29b-41d4-a716-446655440000", "members", "550e8400-e29b-41d4-a716-446655440001"]
            }
          },
          "response": []
        }
      ]
    },
    {
      "name": "Projects",
      "item": [
        {
          "name": "List Projects",
          "request": {
            "method": "GET",
            "header": [],
            "url": {
              "raw": "{{baseUrl}}/projects?workspace=550e8400-e29b-41d4-a716-446655440000&visibility=workspace&page=1&limit=20",
              "host": ["{{baseUrl}}"],
              "path": ["projects"],
              "query": [
                {
                  "key": "workspace",
                  "value": "550e8400-e29b-41d4-a716-446655440000"
                },
                {
                  "key": "visibility",
                  "value": "workspace"
                },
                {
                  "key": "page",
                  "value": "1"
                },
                {
                  "key": "limit",
                  "value": "20"
                }
              ]
            }
          },
          "response": []
        },
        {
          "name": "Create Project",
          "request": {
            "method": "POST",
            "header": [
              {
                "key": "Content-Type",
                "value": "application/json",
                "type": "text"
              }
            ],
            "body": {
              "mode": "raw",
              "raw": "{\n  \"name\": \"Mobile App\",\n  \"description\": \"iOS/Android application\",\n  \"workspace_id\": \"550e8400-e29b-41d4-a716-446655440000\",\n  \"visibility\": \"workspace\"\n}",
              "options": {
                "raw": {
                  "language": "json"
                }
              }
            },
            "url": {
              "raw": "{{baseUrl}}/projects",
              "host": ["{{baseUrl}}"],
              "path": ["projects"]
            }
          },
          "response": []
        },
        {
          "name": "Get Project",
          "request": {
            "method": "GET",
            "header": [],
            "url": {
              "raw": "{{baseUrl}}/projects/550e8400-e29b-41d4-a716-446655440000",
              "host": ["{{baseUrl}}"],
              "path": ["projects", "550e8400-e29b-41d4-a716-446655440000"]
            }
          },
          "response": []
        },
        {
          "name": "Update Project",
          "request": {
            "method": "PATCH",
            "header": [
              {
                "key": "Content-Type",
                "value": "application/json",
                "type": "text"
              }
            ],
            "body": {
              "mode": "raw",
              "raw": "{\n  \"name\": \"Updated Mobile App\",\n  \"description\": \"Updated iOS/Android application\",\n  \"workspace_id\": \"550e8400-e29b-41d4-a716-446655440000\",\n  \"visibility\": \"tenant\"\n}",
              "options": {
                "raw": {
                  "language": "json"
                }
              }
            },
            "url": {
              "raw": "{{baseUrl}}/projects/550e8400-e29b-41d4-a716-446655440000",
              "host": ["{{baseUrl}}"],
              "path": ["projects", "550e8400-e29b-41d4-a716-446655440000"]
            }
          },
          "response": []
        },
        {
          "name": "Delete Project",
          "request": {
            "method": "DELETE",
            "header": [],
            "url": {
              "raw": "{{baseUrl}}/projects/550e8400-e29b-41d4-a716-446655440000",
              "host": ["{{baseUrl}}"],
              "path": ["projects", "550e8400-e29b-41d4-a716-446655440000"]
            }
          },
          "response": []
        }
      ]
    },
    {
      "name": "Tasks",
      "item": [
        {
          "name": "List Tasks",
          "request": {
            "method": "GET",
            "header": [],
            "url": {
              "raw": "{{baseUrl}}/projects/550e8400-e29b-41d4-a716-446655440000/tasks?status=todo&priority=high&assigned_to=550e8400-e29b-41d4-a716-446655440001&page=1&limit=20&search=authentication",
              "host": ["{{baseUrl}}"],
              "path": ["projects", "550e8400-e29b-41d4-a716-446655440000", "tasks"],
              "query": [
                {
                  "key": "status",
                  "value": "todo"
                },
                {
                  "key": "priority",
                  "value": "high"
                },
                {
                  "key": "assigned_to",
                  "value": "550e8400-e29b-41d4-a716-446655440001"
                },
                {
                  "key": "page",
                  "value": "1"
                },
                {
                  "key": "limit",
                  "value": "20"
                },
                {
                  "key": "search",
                  "value": "authentication"
                }
              ]
            }
          },
          "response": []
        },
        {
          "name": "Create Task",
          "request": {
            "method": "POST",
            "header": [
              {
                "key": "Content-Type",
                "value": "application/json",
                "type": "text"
              }
            ],
            "body": {
              "mode": "raw",
              "raw": "{\n  \"title\": \"Implement user authentication\",\n  \"description\": \"Add JWT-based auth system\",\n  \"priority\": \"high\",\n  \"assigned_to\": \"550e8400-e29b-41d4-a716-446655440001\",\n  \"due_date\": \"2024-12-31\",\n  \"estimated_hours\": 8\n}",
              "options": {
                "raw": {
                  "language": "json"
                }
              }
            },
            "url": {
              "raw": "{{baseUrl}}/projects/550e8400-e29b-41d4-a716-446655440000/tasks",
              "host": ["{{baseUrl}}"],
              "path": ["projects", "550e8400-e29b-41d4-a716-446655440000", "tasks"]
            }
          },
          "response": []
        },
        {
          "name": "Get Task",
          "request": {
            "method": "GET",
            "header": [],
            "url": {
              "raw": "{{baseUrl}}/projects/550e8400-e29b-41d4-a716-446655440000/tasks/550e8400-e29b-41d4-a716-446655440002",
              "host": ["{{baseUrl}}"],
              "path": ["projects", "550e8400-e29b-41d4-a716-446655440000", "tasks", "550e8400-e29b-41d4-a716-446655440002"]
            }
          },
          "response": []
        },
        {
          "name": "Update Task",
          "request": {
            "method": "PATCH",
            "header": [
              {
                "key": "Content-Type",
                "value": "application/json",
                "type": "text"
              }
            ],
            "body": {
              "mode": "raw",
              "raw": "{\n  \"title\": \"Updated task title\",\n  \"status\": \"in_progress\",\n  \"priority\": \"critical\",\n  \"description\": \"Updated task description\"\n}",
              "options": {
                "raw": {
                  "language": "json"
                }
              }
            },
            "url": {
              "raw": "{{baseUrl}}/projects/550e8400-e29b-41d4-a716-446655440000/tasks/550e8400-e29b-41d4-a716-446655440002",
              "host": ["{{baseUrl}}"],
              "path": ["projects", "550e8400-e29b-41d4-a716-446655440000", "tasks", "550e8400-e29b-41d4-a716-446655440002"]
            }
          },
          "response": []
        },
        {
          "name": "Delete Task",
          "request": {
            "method": "DELETE",
            "header": [],
            "url": {
              "raw": "{{baseUrl}}/projects/550e8400-e29b-41d4-a716-446655440000/tasks/550e8400-e29b-41d4-a716-446655440002",
              "host": ["{{baseUrl}}"],
              "path": ["projects", "550e8400-e29b-41d4-a716-446655440000", "tasks", "550e8400-e29b-41d4-a716-446655440002"]
            }
          },
          "response": []
        },
        {
          "name": "Assign Task",
          "request": {
            "method": "POST",
            "header": [
              {
                "key": "Content-Type",
                "value": "application/json",
                "type": "text"
              }
            ],
            "body": {
              "mode": "raw",
              "raw": "{\n  \"assigned_to\": \"550e8400-e29b-41d4-a716-446655440001\"\n}",
              "options": {
                "raw": {
                  "language": "json"
                }
              }
            },
            "url": {
              "raw": "{{baseUrl}}/projects/550e8400-e29b-41d4-a716-446655440000/tasks/550e8400-e29b-41d4-a716-446655440002/assign",
              "host": ["{{baseUrl}}"],
              "path": ["projects", "550e8400-e29b-41d4-a716-446655440000", "tasks", "550e8400-e29b-41d4-a716-446655440002", "assign"]
            }
          },
          "response": []
        },
        {
          "name": "Add Task Attachment",
          "request": {
            "method": "POST",
            "header": [
              {
                "key": "Content-Type",
                "value": "application/json",
                "type": "text"
              }
            ],
            "body": {
              "mode": "raw",
              "raw": "{\n  \"filename\": \"document.pdf\",\n  \"s3_key\": \"uploads/tenant_id/file_key\",\n  \"content_type\": \"application/pdf\",\n  \"size\": 1024000\n}",
              "options": {
                "raw": {
                  "language": "json"
                }
              }
            },
            "url": {
              "raw": "{{baseUrl}}/projects/550e8400-e29b-41d4-a716-446655440000/tasks/550e8400-e29b-41d4-a716-446655440002/attachments",
              "host": ["{{baseUrl}}"],
              "path": ["projects", "550e8400-e29b-41d4-a716-446655440000", "tasks", "550e8400-e29b-41d4-a716-446655440002", "attachments"]
            }
          },
          "response": []
        },
        {
          "name": "Remove Task Attachment",
          "request": {
            "method": "DELETE",
            "header": [],
            "url": {
              "raw": "{{baseUrl}}/projects/550e8400-e29b-41d4-a716-446655440000/tasks/550e8400-e29b-41d4-a716-446655440002/attachments/attachment_id",
              "host": ["{{baseUrl}}"],
              "path": ["projects", "550e8400-e29b-41d4-a716-446655440000", "tasks", "550e8400-e29b-41d4-a716-446655440002", "attachments", "attachment_id"]
            }
          },
          "response": []
        }
      ]
    },
    {
      "name": "Comments",
      "item": [
        {
          "name": "List Task Comments",
          "request": {
            "method": "GET",
            "header": [],
            "url": {
              "raw": "{{baseUrl}}/tasks/550e8400-e29b-41d4-a716-446655440002/comments?page=1&limit=20",
              "host": ["{{baseUrl}}"],
              "path": ["tasks", "550e8400-e29b-41d4-a716-446655440002", "comments"],
              "query": [
                {
                  "key": "page",
                  "value": "1"
                },
                {
                  "key": "limit",
                  "value": "20"
                }
              ]
            }
          },
          "response": []
        },
        {
          "name": "Add Comment to Task",
          "request": {
            "method": "POST",
            "header": [
              {
                "key": "Content-Type",
                "value": "application/json",
                "type": "text"
              }
            ],
            "body": {
              "mode": "raw",
              "raw": "{\n  \"text\": \"This looks good to me, approving the change.\"\n}",
              "options": {
                "raw": {
                  "language": "json"
                }
              }
            },
            "url": {
              "raw": "{{baseUrl}}/tasks/550e8400-e29b-41d4-a716-446655440002/comments",
              "host": ["{{baseUrl}}"],
              "path": ["tasks", "550e8400-e29b-41d4-a716-446655440002", "comments"]
            }
          },
          "response": []
        },
        {
          "name": "Get Comment",
          "request": {
            "method": "GET",
            "header": [],
            "url": {
              "raw": "{{baseUrl}}/tasks/550e8400-e29b-41d4-a716-446655440002/comments/550e8400-e29b-41d4-a716-446655440003",
              "host": ["{{baseUrl}}"],
              "path": ["tasks", "550e8400-e29b-41d4-a716-446655440002", "comments", "550e8400-e29b-41d4-a716-446655440003"]
            }
          },
          "response": []
        },
        {
          "name": "Update Comment",
          "request": {
            "method": "PATCH",
            "header": [
              {
                "key": "Content-Type",
                "value": "application/json",
                "type": "text"
              }
            ],
            "body": {
              "mode": "raw",
              "raw": "{\n  \"text\": \"Updated comment text\"\n}",
              "options": {
                "raw": {
                  "language": "json"
                }
              }
            },
            "url": {
              "raw": "{{baseUrl}}/tasks/550e8400-e29b-41d4-a716-446655440002/comments/550e8400-e29b-41d4-a716-446655440003",
              "host": ["{{baseUrl}}"],
              "path": ["tasks", "550e8400-e29b-41d4-a716-446655440002", "comments", "550e8400-e29b-41d4-a716-446655440003"]
            }
          },
          "response": []
        },
        {
          "name": "Delete Comment",
          "request": {
            "method": "DELETE",
            "header": [],
            "url": {
              "raw": "{{baseUrl}}/tasks/550e8400-e29b-41d4-a716-446655440002/comments/550e8400-e29b-41d4-a716-446655440003",
              "host": ["{{baseUrl}}"],
              "path": ["tasks", "550e8400-e29b-41d4-a716-446655440002", "comments", "550e8400-e29b-41d4-a716-446655440003"]
            }
          },
          "response": []
        }
      ]
    },
    {
      "name": "Invites",
      "item": [
        {
          "name": "List Invitations",
          "request": {
            "method": "GET",
            "header": [],
            "url": {
              "raw": "{{baseUrl}}/invites?status=pending&resourceType=workspace&page=1&limit=20",
              "host": ["{{baseUrl}}"],
              "path": ["invites"],
              "query": [
                {
                  "key": "status",
                  "value": "pending"
                },
                {
                  "key": "resourceType",
                  "value": "workspace"
                },
                {
                  "key": "page",
                  "value": "1"
                },
                {
                  "key": "limit",
                  "value": "20"
                }
              ]
            }
          },
          "response": []
        },
        {
          "name": "Create Invitation",
          "request": {
            "method": "POST",
            "header": [
              {
                "key": "Content-Type",
                "value": "application/json",
                "type": "text"
              }
            ],
            "body": {
              "mode": "raw",
              "raw": "{\n  \"email\": \"newuser@domain.com\",\n  \"resourceType\": \"workspace\",\n  \"resourceId\": \"550e8400-e29b-41d4-a716-446655440000\",\n  \"role\": \"member\"\n}",
              "options": {
                "raw": {
                  "language": "json"
                }
              }
            },
            "url": {
              "raw": "{{baseUrl}}/invites",
              "host": ["{{baseUrl}}"],
              "path": ["invites"]
            }
          },
          "response": []
        },
        {
          "name": "Get Invitation",
          "request": {
            "method": "GET",
            "header": [],
            "url": {
              "raw": "{{baseUrl}}/invites/550e8400-e29b-41d4-a716-446655440000",
              "host": ["{{baseUrl}}"],
              "path": ["invites", "550e8400-e29b-41d4-a716-446655440000"]
            }
          },
          "response": []
        },
        {
          "name": "Update Invitation",
          "request": {
            "method": "PATCH",
            "header": [
              {
                "key": "Content-Type",
                "value": "application/json",
                "type": "text"
              }
            ],
            "body": {
              "mode": "raw",
              "raw": "{\n  \"role\": \"admin\"\n}",
              "options": {
                "raw": {
                  "language": "json"
                }
              }
            },
            "url": {
              "raw": "{{baseUrl}}/invites/550e8400-e29b-41d4-a716-446655440000",
              "host": ["{{baseUrl}}"],
              "path": ["invites", "550e8400-e29b-41d4-a716-446655440000"]
            }
          },
          "response": []
        },
        {
          "name": "Cancel Invitation",
          "request": {
            "method": "DELETE",
            "header": [],
            "url": {
              "raw": "{{baseUrl}}/invites/550e8400-e29b-41d4-a716-446655440000",
              "host": ["{{baseUrl}}"],
              "path": ["invites", "550e8400-e29b-41d4-a716-446655440000"]
            }
          },
          "response": []
        },
        {
          "name": "Accept Invitation",
          "request": {
            "method": "POST",
            "header": [],
            "url": {
              "raw": "{{baseUrl}}/invites/550e8400-e29b-41d4-a716-446655440000/accept",
              "host": ["{{baseUrl}}"],
              "path": ["invites", "550e8400-e29b-41d4-a716-446655440000", "accept"]
            }
          },
          "response": []
        },
        {
          "name": "Decline Invitation",
          "request": {
            "method": "POST",
            "header": [],
            "url": {
              "raw": "{{baseUrl}}/invites/550e8400-e29b-41d4-a716-446655440000/decline",
              "host": ["{{baseUrl}}"],
              "path": ["invites", "550e8400-e29b-41d4-a716-446655440000", "decline"]
            }
          },
          "response": []
        }
      ]
    },
    {
      "name": "Files",
      "item": [
        {
          "name": "Get Presigned Upload URL",
          "request": {
            "method": "POST",
            "header": [
              {
                "key": "Content-Type",
                "value": "application/json",
                "type": "text"
              }
            ],
            "body": {
              "mode": "raw",
              "raw": "{\n  \"fileName\": \"document.pdf\",\n  \"contentType\": \"application/pdf\",\n  \"size\": 1024000,\n  \"taskId\": \"550e8400-e29b-41d4-a716-446655440002\"\n}",
              "options": {
                "raw": {
                  "language": "json"
                }
              }
            },
            "url": {
              "raw": "{{baseUrl}}/files/presign",
              "host": ["{{baseUrl}}"],
              "path": ["files", "presign"]
            }
          },
          "response": []
        },
        {
          "name": "Antivirus Scan Callback",
          "request": {
            "auth": {
              "type": "noauth"
            },
            "method": "POST",
            "header": [
              {
                "key": "Content-Type",
                "value": "application/json",
                "type": "text"
              }
            ],
            "body": {
              "mode": "raw",
              "raw": "{\n  \"key\": \"uploads/tenant_id/file_key\",\n  \"clean\": true,\n  \"taskId\": \"550e8400-e29b-41d4-a716-446655440002\",\n  \"tenantId\": \"550e8400-e29b-41d4-a716-446655440000\"\n}",
              "options": {
                "raw": {
                  "language": "json"
                }
              }
            },
            "url": {
              "raw": "{{baseUrl}}/files/scan-callback",
              "host": ["{{baseUrl}}"],
              "path": ["files", "scan-callback"]
            }
          },
          "response": []
        }
      ]
    },
    {
      "name": "Activity Logs",
      "item": [
        {
          "name": "Get Activity Logs",
          "request": {
            "method": "GET",
            "header": [],
            "url": {
              "raw": "{{baseUrl}}/activity?resource_type=task&resource_id=550e8400-e29b-41d4-a716-446655440002&action=created&user_id=550e8400-e29b-41d4-a716-446655440001&from_date=2024-01-01&to_date=2024-12-31&page=1&limit=20",
              "host": ["{{baseUrl}}"],
              "path": ["activity"],
              "query": [
                {
                  "key": "resource_type",
                  "value": "task"
                },
                {
                  "key": "resource_id",
                  "value": "550e8400-e29b-41d4-a716-446655440002"
                },
                {
                  "key": "action",
                  "value": "created"
                },
                {
                  "key": "user_id",
                  "value": "550e8400-e29b-41d4-a716-446655440001"
                },
                {
                  "key": "from_date",
                  "value": "2024-01-01"
                },
                {
                  "key": "to_date",
                  "value": "2024-12-31"
                },
                {
                  "key": "page",
                  "value": "1"
                },
                {
                  "key": "limit",
                  "value": "20"
                }
              ]
            }
          },
          "response": []
        }
      ]
    },
    {
      "name": "Monitoring",
      "item": [
        {
          "name": "Health Check",
          "request": {
            "auth": {
              "type": "noauth"
            },
            "method": "GET",
            "header": [],
            "url": {
              "raw": "{{baseUrl}}/monitoring/health",
              "host": ["{{baseUrl}}"],
              "path": ["monitoring", "health"]
            }
          },
          "response": []
        },
        {
          "name": "Prometheus Metrics",
          "request": {
            "auth": {
              "type": "noauth"
            },
            "method": "GET",
            "header": [],
            "url": {
              "raw": "{{baseUrl}}/monitoring/metrics",
              "host": ["{{baseUrl}}"],
              "path": ["monitoring", "metrics"]
            }
          },
          "response": []
        }
      ]
    }
  ]
}